geco_auth/__init__.py
geco_auth/asgi.py
geco_auth/settings.py
geco_auth/urls.py
geco_auth/wsgi.py
gecoauth/__init__.py
gecoauth/admin.py
gecoauth/apps.py
gecoauth/models.py
gecoauth/serializers.py
gecoauth/tests.py
gecoauth/urls.py
gecoauth/views.py
gecoauth/migrations/0001_initial.py
gecoauth/migrations/__init__.py
gecoauth-0.3.0.dist-info/LICENSE
gecoauth-0.3.0.dist-info/METADATA
gecoauth-0.3.0.dist-info/WHEEL
gecoauth-0.3.0.dist-info/top_level.txt
gecoauth-0.3.0.dist-info/RECORD
