Metadata-Version: 2.1
Name: gecoauth
Version: 0.3.0
Summary: A Django app that extends django-rest-auth.
Home-page: https://github.com/Plutone11011/geco_auth.git
Author: Lorenzo Borelli
Author-email: lorenzo.borelli@gecosistema.com
License: MIT
Platform: UNKNOWN
Classifier: Environment :: Web Environment
Classifier: Framework :: Django
Classifier: Intended Audience :: Developers
Classifier: License :: OSI Approved :: BSD License
Classifier: Operating System :: OS Independent
Classifier: Programming Language :: Python
Classifier: Programming Language :: Python :: 3
Classifier: Programming Language :: Python :: 3 :: Only
Classifier: Programming Language :: Python :: 3.6
Classifier: Programming Language :: Python :: 3.7
Classifier: Programming Language :: Python :: 3.8
Classifier: Topic :: Internet :: WWW/HTTP
Classifier: Topic :: Internet :: WWW/HTTP :: Dynamic Content
Requires-Dist: Django
Requires-Dist: django-allauth
Requires-Dist: django-rest-auth
Requires-Dist: djangorestframework
